qy_app/__init__.py
qy_app/client.py
xqywx-0.3.0.dist-info/METADATA
xqywx-0.3.0.dist-info/WHEEL
xqywx-0.3.0.dist-info/top_level.txt
xqywx-0.3.0.dist-info/RECORD
